pyphewas/__init__.py
pyphewas/config.json
pyphewas/model_formatters.py
pyphewas/parser/__init__.py
pyphewas/parser/cmd_parser.py
pyphewas/phecode_maps/phecode12.csv
pyphewas/phecode_maps/phecodeX.csv
pyphewas/phecode_maps/phecodeX_WHO.csv
pyphewas/plotting.py
pyphewas/run_PheWAS.py
pyphewas_package-0.4.2.dist-info/METADATA
pyphewas_package-0.4.2.dist-info/WHEEL
pyphewas_package-0.4.2.dist-info/entry_points.txt
pyphewas_package-0.4.2.dist-info/licenses/LICENSE
pyphewas_package-0.4.2.dist-info/RECORD
