Metadata-Version: 2.1
Name: pyphewas-package
Version: 0.4.2
Summary: CLI tool to run a PheWAS
Author-Email: James Baker <james.baker@vanderbilt.edu>
License: Apache-2.0
Requires-Python: >3.11.0
Requires-Dist: polars>=1.31.0
Requires-Dist: xopen>=2.0.2
Requires-Dist: rich-argparse>=1.7.1
Requires-Dist: statsmodels>=0.14.4
Requires-Dist: tqdm>=4.67.1
Requires-Dist: matplotlib>=3.10.3
Requires-Dist: adjusttext>=1.3.0
Requires-Dist: seaborn>=0.13.2
Requires-Dist: pyarrow>=22.0.0
Requires-Dist: firthmodels>=0.1.1
Requires-Dist: patsy>=1.0.2
Provides-Extra: docs
Requires-Dist: sphinx>=8.1.3; extra == "docs"
Requires-Dist: sphinx-autobuild>=2024.10.3; extra == "docs"
Requires-Dist: sphinx-copybutton>=0.5.2; extra == "docs"
Requires-Dist: sphinx-book-theme>=1.1.4; extra == "docs"
